exe.py
exe-0.9.0.dist-info/METADATA
exe-0.9.0.dist-info/WHEEL
exe-0.9.0.dist-info/top_level.txt
exe-0.9.0.dist-info/RECORD
