Metadata-Version: 2.1
Name: exe
Version: 0.9.0
Requires-Dist: ccompiler
